libschrodinger/__init__.py
libschrodinger/config.py
libschrodinger/constants.py
libschrodinger/electron.py
libschrodinger/figlocation.py
libschrodinger/gauss.py
libschrodinger/graphs.py
libschrodinger/interaction.py
libschrodinger/particle.py
libschrodinger/potential.py
libschrodinger/waveutils.py
libschrodinger/quark/__init__.py
libschrodinger/quark/baryon.py
libschrodinger/quark/color.py
libschrodinger/quark/hadron.py
libschrodinger/quark/meson.py
libschrodinger/quark/quark.py
libschrodinger-1.3.2.dist-info/LICENSE
libschrodinger-1.3.2.dist-info/METADATA
libschrodinger-1.3.2.dist-info/WHEEL
libschrodinger-1.3.2.dist-info/top_level.txt
libschrodinger-1.3.2.dist-info/RECORD
