Metadata-Version: 2.1
Name: libschrodinger
Version: 1.3.2
Summary: A small package for simulating quantum-scale physics.
Author-email: 1p22geo <1p22geodecki@gmail.com>, KacperTZSTI <kacper.m.trzop@gmail.com>
Project-URL: Homepage, https://github.com/1p22geo/schrodinger
Project-URL: Issues, https://github.com/1p22geo/schrodinger/issues
Classifier: Programming Language :: Python :: 3
Classifier: License :: OSI Approved :: GNU General Public License v3 (GPLv3)
Classifier: Operating System :: OS Independent
Requires-Python: >=3.8
License-File: LICENSE
Requires-Dist: numpy
Requires-Dist: scipy
Requires-Dist: matplotlib
